gmailnotipy/__init__.py
gmailnotipy/gmailnotipy.py
gmailnotipy-0.0.5.dist-info/LICENSE
gmailnotipy-0.0.5.dist-info/METADATA
gmailnotipy-0.0.5.dist-info/WHEEL
gmailnotipy-0.0.5.dist-info/entry_points.txt
gmailnotipy-0.0.5.dist-info/top_level.txt
gmailnotipy-0.0.5.dist-info/RECORD
