Metadata-Version: 2.1
Name: gmailnotipy
Version: 0.0.5
Summary: A command line tool which will notify when an email arrives in your Gmail inbox.
Home-page: https://github.com/iamtalhaasghar/gmailnotipy
Author: Talha Asghar
Author-email: talhaasghar.contact@simplelogin.fr
License: UNKNOWN
Platform: UNKNOWN
Classifier: Programming Language :: Python :: 3
Classifier: License :: OSI Approved :: GNU General Public License v3 (GPLv3)
Classifier: Operating System :: OS Independent
Requires-Python: >=3.0
License-File: LICENSE
Requires-Dist: py-notifier (==0.3.2)
